{"chunk_definitions":[{"row":9,"row_count":1,"visible":true,"expansion_state":0,"options":{"engine":"r","dev":"png"},"document_id":"9002A2D4","chunk_id":"csetup_chunk","chunk_label":"setup"},{"row":19,"row_count":1,"visible":true,"expansion_state":0,"options":{"engine":"r","dev":"png"},"document_id":"9002A2D4","chunk_id":"cw3guufz1a23r","chunk_label":"unnamed-chunk-1"},{"row":28,"row_count":1,"visible":true,"expansion_state":0,"options":{"engine":"r","label":"unnamed-chunk-734","dev":"png"},"document_id":"9002A2D4","chunk_id":"c9sgb2w7uiqgh","chunk_label":"unnamed-chunk-2"},{"row":63,"row_count":1,"visible":true,"expansion_state":0,"options":{"engine":"r","label":"unnamed-chunk-631","dev":"png"},"document_id":"9002A2D4","chunk_id":"c56pyio21tew4","chunk_label":"unnamed-chunk-4"},{"row":87,"row_count":1,"visible":true,"expansion_state":0,"options":{"engine":"r","label":"unnamed-chunk-313","dev":"png"},"document_id":"9002A2D4","chunk_id":"cjhuktfx9z9oy","chunk_label":"unnamed-chunk-5"},{"row":138,"row_count":1,"visible":true,"expansion_state":0,"options":{"engine":"r","label":"unnamed-chunk-160","dev":"png"},"document_id":"9002A2D4","chunk_id":"c99vlh2ckrkp3","chunk_label":"unnamed-chunk-8"},{"row":180,"row_count":1,"visible":true,"expansion_state":0,"options":{"engine":"r","label":"unnamed-chunk-743","dev":"png"},"document_id":"9002A2D4","chunk_id":"cq855f6xzl4q9","chunk_label":"unnamed-chunk-10"},{"row":198,"row_count":1,"visible":true,"expansion_state":0,"options":{"engine":"r","dev":"png"},"document_id":"9002A2D4","chunk_id":"cmjbkfuup677y","chunk_label":"unnamed-chunk-11"}],"doc_write_time":1210234165248,"working_dir":null,"default_chunk_options":{"echo":true},"chunk_rendered_width":700}